{"nodes": [{"id": "round_1_scratch_check_linear_py", "label": "check_linear.py", "file_type": "code", "source_file": "ROUND 1\\scratch\\check_linear.py", "source_location": "L1"}, {"id": "check_linear_analyze_linear", "label": "analyze_linear()", "file_type": "code", "source_file": "ROUND 1\\scratch\\check_linear.py", "source_location": "L4"}], "edges": [{"source": "round_1_scratch_check_linear_py", "target": "pandas", "relation": "imports", "confidence": "EXTRACTED", "source_file": "ROUND 1\\scratch\\check_linear.py", "source_location": "L1", "weight": 1.0}, {"source": "round_1_scratch_check_linear_py", "target": "numpy", "relation": "imports", "confidence": "EXTRACTED", "source_file": "ROUND 1\\scratch\\check_linear.py", "source_location": "L2", "weight": 1.0}, {"source": "round_1_scratch_check_linear_py", "target": "check_linear_analyze_linear", "relation": "contains", "confidence": "EXTRACTED", "source_file": "ROUND 1\\scratch\\check_linear.py", "source_location": "L4", "weight": 1.0}], "raw_calls": [{"caller_nid": "check_linear_analyze_linear", "callee": "read_csv", "source_file": "ROUND 1\\scratch\\check_linear.py", "source_location": "L7"}, {"caller_nid": "check_linear_analyze_linear", "callee": "print", "source_file": "ROUND 1\\scratch\\check_linear.py", "source_location": "L9"}, {"caller_nid": "check_linear_analyze_linear", "callee": "dropna", "source_file": "ROUND 1\\scratch\\check_linear.py", "source_location": "L12"}, {"caller_nid": "check_linear_analyze_linear", "callee": "pivot", "source_file": "ROUND 1\\scratch\\check_linear.py", "source_location": "L12"}, {"caller_nid": "check_linear_analyze_linear", "callee": "vstack", "source_file": "ROUND 1\\scratch\\check_linear.py", "source_location": "L18"}, {"caller_nid": "check_linear_analyze_linear", "callee": "ones", "source_file": "ROUND 1\\scratch\\check_linear.py", "source_location": "L18"}, {"caller_nid": "check_linear_analyze_linear", "callee": "len", "source_file": "ROUND 1\\scratch\\check_linear.py", "source_location": "L18"}, {"caller_nid": "check_linear_analyze_linear", "callee": "lstsq", "source_file": "ROUND 1\\scratch\\check_linear.py", "source_location": "L19"}, {"caller_nid": "check_linear_analyze_linear", "callee": "sum", "source_file": "ROUND 1\\scratch\\check_linear.py", "source_location": "L23"}, {"caller_nid": "check_linear_analyze_linear", "callee": "sum", "source_file": "ROUND 1\\scratch\\check_linear.py", "source_location": "L24"}, {"caller_nid": "check_linear_analyze_linear", "callee": "mean", "source_file": "ROUND 1\\scratch\\check_linear.py", "source_location": "L24"}, {"caller_nid": "check_linear_analyze_linear", "callee": "print", "source_file": "ROUND 1\\scratch\\check_linear.py", "source_location": "L27"}, {"caller_nid": "check_linear_analyze_linear", "callee": "print", "source_file": "ROUND 1\\scratch\\check_linear.py", "source_location": "L28"}, {"caller_nid": "check_linear_analyze_linear", "callee": "print", "source_file": "ROUND 1\\scratch\\check_linear.py", "source_location": "L29"}]}