{"nodes": [{"id": "imc_prosperity_4_backtester_prosperity4bt_file_reader_py", "label": "file_reader.py", "file_type": "code", "source_file": "imc-prosperity-4-backtester\\prosperity4bt\\file_reader.py", "source_location": "L1"}, {"id": "file_reader_wrap_in_context_manager", "label": "wrap_in_context_manager()", "file_type": "code", "source_file": "imc-prosperity-4-backtester\\prosperity4bt\\file_reader.py", "source_location": "L9"}, {"id": "file_reader_filereader", "label": "FileReader", "file_type": "code", "source_file": "imc-prosperity-4-backtester\\prosperity4bt\\file_reader.py", "source_location": "L13"}, {"id": "file_reader_file", "label": "file()", "file_type": "code", "source_file": "imc-prosperity-4-backtester\\prosperity4bt\\file_reader.py", "source_location": "L15"}, {"id": "file_reader_filesystemreader", "label": "FileSystemReader", "file_type": "code", "source_file": "imc-prosperity-4-backtester\\prosperity4bt\\file_reader.py", "source_location": "L20"}, {"id": "file_reader_filesystemreader_init", "label": ".__init__()", "file_type": "code", "source_file": "imc-prosperity-4-backtester\\prosperity4bt\\file_reader.py", "source_location": "L21"}, {"id": "file_reader_filesystemreader_file", "label": ".file()", "file_type": "code", "source_file": "imc-prosperity-4-backtester\\prosperity4bt\\file_reader.py", "source_location": "L24"}, {"id": "file_reader_packageresourcesreader", "label": "PackageResourcesReader", "file_type": "code", "source_file": "imc-prosperity-4-backtester\\prosperity4bt\\file_reader.py", "source_location": "L35"}, {"id": "file_reader_packageresourcesreader_file", "label": ".file()", "file_type": "code", "source_file": "imc-prosperity-4-backtester\\prosperity4bt\\file_reader.py", "source_location": "L36"}, {"id": "file_reader_rationale_16", "label": "Given a path to a file, yields a single Path object to the file or None if the f", "file_type": "rationale", "source_file": "imc-prosperity-4-backtester\\prosperity4bt\\file_reader.py", "source_location": "L16"}], "edges": [{"source": "imc_prosperity_4_backtester_prosperity4bt_file_reader_py", "target": "abc", "relation": "imports_from", "confidence": "EXTRACTED", "source_file": "imc-prosperity-4-backtester\\prosperity4bt\\file_reader.py", "source_location": "L1", "weight": 1.0}, {"source": "imc_prosperity_4_backtester_prosperity4bt_file_reader_py", "target": "contextlib", "relation": "imports_from", "confidence": "EXTRACTED", "source_file": "imc-prosperity-4-backtester\\prosperity4bt\\file_reader.py", "source_location": "L2", "weight": 1.0}, {"source": "imc_prosperity_4_backtester_prosperity4bt_file_reader_py", "target": "importlib", "relation": "imports_from", "confidence": "EXTRACTED", "source_file": "imc-prosperity-4-backtester\\prosperity4bt\\file_reader.py", "source_location": "L3", "weight": 1.0}, {"source": "imc_prosperity_4_backtester_prosperity4bt_file_reader_py", "target": "pathlib", "relation": "imports_from", "confidence": "EXTRACTED", "source_file": "imc-prosperity-4-backtester\\prosperity4bt\\file_reader.py", "source_location": "L4", "weight": 1.0}, {"source": "imc_prosperity_4_backtester_prosperity4bt_file_reader_py", "target": "typing", "relation": "imports_from", "confidence": "EXTRACTED", "source_file": "imc-prosperity-4-backtester\\prosperity4bt\\file_reader.py", "source_location": "L5", "weight": 1.0}, {"source": "imc_prosperity_4_backtester_prosperity4bt_file_reader_py", "target": "file_reader_wrap_in_context_manager", "relation": "contains", "confidence": "EXTRACTED", "source_file": "imc-prosperity-4-backtester\\prosperity4bt\\file_reader.py", "source_location": "L9", "weight": 1.0}, {"source": "imc_prosperity_4_backtester_prosperity4bt_file_reader_py", "target": "file_reader_filereader", "relation": "contains", "confidence": "EXTRACTED", "source_file": "imc-prosperity-4-backtester\\prosperity4bt\\file_reader.py", "source_location": "L13", "weight": 1.0}, {"source": "imc_prosperity_4_backtester_prosperity4bt_file_reader_py", "target": "file_reader_file", "relation": "contains", "confidence": "EXTRACTED", "source_file": "imc-prosperity-4-backtester\\prosperity4bt\\file_reader.py", "source_location": "L15", "weight": 1.0}, {"source": "imc_prosperity_4_backtester_prosperity4bt_file_reader_py", "target": "file_reader_filesystemreader", "relation": "contains", "confidence": "EXTRACTED", "source_file": "imc-prosperity-4-backtester\\prosperity4bt\\file_reader.py", "source_location": "L20", "weight": 1.0}, {"source": "file_reader_filesystemreader", "target": "file_reader_filereader", "relation": "inherits", "confidence": "EXTRACTED", "source_file": "imc-prosperity-4-backtester\\prosperity4bt\\file_reader.py", "source_location": "L20", "weight": 1.0}, {"source": "file_reader_filesystemreader", "target": "file_reader_filesystemreader_init", "relation": "method", "confidence": "EXTRACTED", "source_file": "imc-prosperity-4-backtester\\prosperity4bt\\file_reader.py", "source_location": "L21", "weight": 1.0}, {"source": "file_reader_filesystemreader", "target": "file_reader_filesystemreader_file", "relation": "method", "confidence": "EXTRACTED", "source_file": "imc-prosperity-4-backtester\\prosperity4bt\\file_reader.py", "source_location": "L24", "weight": 1.0}, {"source": "imc_prosperity_4_backtester_prosperity4bt_file_reader_py", "target": "file_reader_packageresourcesreader", "relation": "contains", "confidence": "EXTRACTED", "source_file": "imc-prosperity-4-backtester\\prosperity4bt\\file_reader.py", "source_location": "L35", "weight": 1.0}, {"source": "file_reader_packageresourcesreader", "target": "file_reader_filereader", "relation": "inherits", "confidence": "EXTRACTED", "source_file": "imc-prosperity-4-backtester\\prosperity4bt\\file_reader.py", "source_location": "L35", "weight": 1.0}, {"source": "file_reader_packageresourcesreader", "target": "file_reader_packageresourcesreader_file", "relation": "method", "confidence": "EXTRACTED", "source_file": "imc-prosperity-4-backtester\\prosperity4bt\\file_reader.py", "source_location": "L36", "weight": 1.0}, {"source": "file_reader_filesystemreader_file", "target": "file_reader_wrap_in_context_manager", "relation": "calls", "confidence": "EXTRACTED", "source_file": "imc-prosperity-4-backtester\\prosperity4bt\\file_reader.py", "source_location": "L30", "weight": 1.0}, {"source": "file_reader_packageresourcesreader_file", "target": "file_reader_wrap_in_context_manager", "relation": "calls", "confidence": "EXTRACTED", "source_file": "imc-prosperity-4-backtester\\prosperity4bt\\file_reader.py", "source_location": "L41", "weight": 1.0}, {"source": "file_reader_rationale_16", "target": "file_reader_filereader_file", "relation": "rationale_for", "confidence": "EXTRACTED", "source_file": "imc-prosperity-4-backtester\\prosperity4bt\\file_reader.py", "source_location": "L16", "weight": 1.0}], "raw_calls": [{"caller_nid": "file_reader_file", "callee": "NotImplementedError", "source_file": "imc-prosperity-4-backtester\\prosperity4bt\\file_reader.py", "source_location": "L17"}, {"caller_nid": "file_reader_filesystemreader_file", "callee": "is_file", "source_file": "imc-prosperity-4-backtester\\prosperity4bt\\file_reader.py", "source_location": "L29"}, {"caller_nid": "file_reader_packageresourcesreader_file", "callee": "files", "source_file": "imc-prosperity-4-backtester\\prosperity4bt\\file_reader.py", "source_location": "L38"}, {"caller_nid": "file_reader_packageresourcesreader_file", "callee": "join", "source_file": "imc-prosperity-4-backtester\\prosperity4bt\\file_reader.py", "source_location": "L38"}, {"caller_nid": "file_reader_packageresourcesreader_file", "callee": "is_file", "source_file": "imc-prosperity-4-backtester\\prosperity4bt\\file_reader.py", "source_location": "L40"}, {"caller_nid": "file_reader_packageresourcesreader_file", "callee": "as_file", "source_file": "imc-prosperity-4-backtester\\prosperity4bt\\file_reader.py", "source_location": "L43"}]}